PySLAM-1.2.1.data/scripts/pyslam
PySLAM-1.2.1.data/scripts/pyslam-ytdl
pyslam/setup.py
pyslam/slam.py
PySLAM-1.2.1.dist-info/LICENSE.md
PySLAM-1.2.1.dist-info/LICENSE.txt
PySLAM-1.2.1.dist-info/METADATA
PySLAM-1.2.1.dist-info/WHEEL
PySLAM-1.2.1.dist-info/top_level.txt
PySLAM-1.2.1.dist-info/RECORD
